README.rst
setup.py
preprint/__init__.py
preprint/config.py
preprint/init.py
preprint/latexdiff.py
preprint/main.py
preprint/make.py
preprint/pack.py
preprint/vc.py
preprint/watch.py
preprint.egg-info/PKG-INFO
preprint.egg-info/SOURCES.txt
preprint.egg-info/dependency_links.txt
preprint.egg-info/entry_points.txt
preprint.egg-info/namespace_packages.txt
preprint.egg-info/not-zip-safe
preprint.egg-info/pbr.json
preprint.egg-info/requires.txt
preprint.egg-info/top_level.txt