Metadata-Version: 1.1
Name: preprint
Version: 0.2.2
Summary: Tools for writing latex papers
Home-page: https://github.com/jonathansick/preprint
Author: Jonathan Sick
Author-email: jonathansick@mac.com
License: UNKNOWN
Platform: Any
Classifier: Development Status :: 3 - Alpha
Classifier: Programming Language :: Python
Classifier: Programming Language :: Python :: 2
Classifier: Programming Language :: Python :: 2.7
Classifier: Environment :: Console
